shmakovpn/__init__.py
shmakovpn/example.py
shmakovpn/tests.py
shmakovpn/version.py
shmakovpn_tools-1.1.dist-info/LICENSE.txt
shmakovpn_tools-1.1.dist-info/METADATA
shmakovpn_tools-1.1.dist-info/WHEEL
shmakovpn_tools-1.1.dist-info/top_level.txt
shmakovpn_tools-1.1.dist-info/RECORD
