Metadata-Version: 2.1
Name: shmakovpn-tools
Version: 1.1
Summary: UNKNOWN
Home-page: https://github.com/shmakovpn/shmakovpn_tools
Author: shmakovpn
Author-email: shmakovpn@yandex.ru
License: UNKNOWN
Download-URL: https://github.com/shmakovpn/shmakovpn_tools/archive/1.1.zip
Platform: UNKNOWN
Classifier: Programming Language :: Python :: 3
Classifier: License :: OSI Approved :: Apache Software License
Classifier: Operating System :: OS Independent
Requires-Python: >=3.6
